colorzero/__init__.py
colorzero/attr.py
colorzero/color.py
colorzero/conversions.py
colorzero/deltae.py
colorzero/easings.py
colorzero/tables.py
colorzero/types.py
colorzero-2.0.dist-info/LICENSE.txt
colorzero-2.0.dist-info/METADATA
colorzero-2.0.dist-info/WHEEL
colorzero-2.0.dist-info/top_level.txt
colorzero-2.0.dist-info/RECORD
