Metadata-Version: 2.1
Name: colorzero
Version: 2.0
Summary: Yet another Python color library
Home-page: UNKNOWN
Author: Dave Jones
Author-email: dave@waveform.org.uk
License: BSD-3-Clause
Project-URL: Documentation, https://colorzero.readthedocs.io/
Project-URL: Source Code, https://github.com/waveform80/colorzero/
Project-URL: Issue Tracker, https://github.com/waveform80/colorzero/issues
Keywords: color
Platform: UNKNOWN
Classifier: Development Status :: 5 - Production/Stable
Classifier: Intended Audience :: Education
Classifier: Intended Audience :: Developers
Classifier: Topic :: Education
Classifier: License :: OSI Approved :: BSD License
Classifier: Programming Language :: Python :: 3
Classifier: Programming Language :: Python :: 3.5
Classifier: Programming Language :: Python :: 3.6
Classifier: Programming Language :: Python :: 3.7
Classifier: Programming Language :: Python :: 3.8
Classifier: Programming Language :: Python :: 3.9
Classifier: Programming Language :: Python :: Implementation :: PyPy
Provides-Extra: test
Provides-Extra: doc
